apiverve_counter/__init__.py
apiverve_counter/apiClient.py
apiverve_counter/exceptions.py
apiverve_counter/setup.py
apiverve_counter/tests/__init__.py
apiverve_counter/tests/test_api.py
apiverve_counter-1.0.11.dist-info/LICENSE
apiverve_counter-1.0.11.dist-info/METADATA
apiverve_counter-1.0.11.dist-info/WHEEL
apiverve_counter-1.0.11.dist-info/top_level.txt
apiverve_counter-1.0.11.dist-info/RECORD
